gradient_descent.cpython-37m-darwin.so
lin_reg.cpython-37m-darwin.so
ml/__init__.py
ml/activation/__init__.py
ml/activation/functions.py
ml/cnn/__init__.py
ml/cnn/cnn2d.py
ml/data/__init__.py
ml/data/functions.py
ml/error/__init__.py
ml/error/error.py
ml/graph/__init__.py
ml/graph/function.py
ml/graph/kmeans/__init__.py
ml/graph/kmeans/graph.py
ml/graph/lr/__init__.py
ml/graph/lr/graph.py
ml/k_means/__init__.py
ml/k_means/kmeans.py
ml/linear_regression/__init__.py
ml/linear_regression/lreg.py
ml/linear_regression/setup.py
ml/linear_regression/test_lr.py
ml/logistic_regression/__init__.py
ml/logistic_regression/logistic_regression.py
ml/nn/__init__.py
ml/nn/neuralnetwork.py
ml/optimizer/__init__.py
ml/optimizer/_adam.py
ml/optimizer/adam_test.py
ml/optimizer/gdescent.py
ml/optimizer/optimizer_test.py
ml/optimizer/setup.py
ml/optimizer/setup_a.py
ml/optimizer/setup_g.py
ml/random/__init__.py
ml/random/datasets.py
ml/random/kmeans/__init__.py
ml/random/kmeans/clusters.py
ml/regression/__init__.py
ml/regression/regression.py
ml/rnn/__init__.py
ml/rnn/rnn.py
ml_python-2.3.1.dist-info/LICENSE.md
ml_python-2.3.1.dist-info/METADATA
ml_python-2.3.1.dist-info/WHEEL
ml_python-2.3.1.dist-info/top_level.txt
ml_python-2.3.1.dist-info/RECORD
