Metadata-Version: 2.1
Name: ml-python
Version: 2.3.1
Summary: The easiest way to do machine learning
Home-page: https://github.com/vivek3141/ml
Author: Vivek Verma
Author-email: vivekverma3141@gmail.com
License: MIT
Platform: UNKNOWN
Classifier: Programming Language :: Python :: 3
Classifier: Programming Language :: Python :: 2
Classifier: License :: OSI Approved :: MIT License
Classifier: Operating System :: OS Independent
